README.md
main.py
mini_agent_action-0.1.4.dist-info/METADATA
mini_agent_action-0.1.4.dist-info/WHEEL
mini_agent_action-0.1.4.dist-info/entry_points.txt
mini_agent_action-0.1.4.dist-info/RECORD
