Metadata-Version: 2.4
Name: mini-agent-action
Version: 0.1.4
Summary: Add your description here
Requires-Python: >=3.11
Requires-Dist: mini-swe-agent>=1.11.1
